{"6417845887": [{"code": "773673", "session_id": "12cf3e9e00f64d2cacf13bf67c588f8d", "plan": "Unknown", "balance": {}}, {"code": "246834", "session_id": "47762dc48eb84ab6b170ab670a90461f", "plan": "Unknown", "balance": {}}, {"code": "380303", "session_id": "b29f0368e8d24905bfda507f4dd4330e", "plan": "Unknown", "balance": {}}, {"code": "370447", "session_id": "b3fa496f9f264d33b6c8e2a9144b0ec2", "plan": "Unknown", "balance": {}}, {"code": "373835", "session_id": "2aba940523c34160b239830781d1b6c8", "plan": "Unknown", "balance": {}}]}